space_tracer/__init__.py
space_tracer/__main__.py
space_tracer/about.py
space_tracer/canvas.py
space_tracer/code_tracer.py
space_tracer/live_image.py
space_tracer/main.py
space_tracer/mock_turtle.py
space_tracer/module_importers.py
space_tracer/py.typed
space_tracer/report_builder.py
space_tracer/traced_finder.py
space_tracer-4.13.0.dist-info/licenses/license.txt
space_tracer-4.13.0.dist-info/METADATA
space_tracer-4.13.0.dist-info/WHEEL
space_tracer-4.13.0.dist-info/entry_points.txt
space_tracer-4.13.0.dist-info/top_level.txt
space_tracer-4.13.0.dist-info/RECORD
