Metadata-Version: 2.4
Name: space_tracer
Version: 4.13.0
Summary: Trade time for space when debugging your code.
Author: Don Kirkby
Author-email: donkirkby@gmail.com
License-Expression: MIT
Project-URL: Source, https://github.com/donkirkby/live-py-plugin
Project-URL: Issues, https://github.com/donkirkby/live-py-plugin/issues
Classifier: Intended Audience :: Developers
Classifier: Topic :: Software Development :: Debuggers
Classifier: Programming Language :: Python :: 3.8
Classifier: Programming Language :: Python :: 3.9
Classifier: Programming Language :: Python :: 3.10
Classifier: Programming Language :: Python :: 3.11
Classifier: Programming Language :: Python :: 3.12
Classifier: Programming Language :: Python :: 3.13
Classifier: Programming Language :: Python :: 3.14
Classifier: Operating System :: OS Independent
Classifier: Development Status :: 5 - Production/Stable
Classifier: Environment :: Console
License-File: license.txt
Requires-Dist: svgwrite
Dynamic: author
Dynamic: author-email
Dynamic: license-file
Dynamic: summary
